{
    "stream": "next",
    "metadata": {
        "last-modified": "2024-08-15T00:33:27Z",
        "generator": "fedora-coreos-stream-generator v0.2.15"
    },
    "architectures": {
        "aarch64": {
            "artifacts": {
                "applehv": {
                    "release": "40.20240808.1.0",
                    "formats": {
                        "raw.gz": {
                            "disk": {
                                "location": "https://builds.coreos.fedoraproject.org/prod/streams/next/builds/40.20240808.1.0/aarch64/fedora-coreos-40.20240808.1.0-applehv.aarch64.raw.gz",
                                "signature": "https://builds.coreos.fedoraproject.org/prod/streams/next/builds/40.20240808.1.0/aarch64/fedora-coreos-40.20240808.1.0-applehv.aarch64.raw.gz.sig",
                                "sha256": "f5c38d661c9a0249237a28ce9b1a138558d54c1ceca0fc7c8675d06a5d011aaf",
                                "uncompressed-sha256": "9c470246f17938164c5650afee686cf5d806d82b4d37811185cbafc68700ecee"
                            }
                        }
                    }
                },
                "aws": {
                    "release": "40.20240808.1.0",
                    "formats": {
                        "vmdk.xz": {
                            "disk": {
                                "location": "https://builds.coreos.fedoraproject.org/prod/streams/next/builds/40.20240808.1.0/aarch64/fedora-coreos-40.20240808.1.0-aws.aarch64.vmdk.xz",
                                "signature": "https://builds.coreos.fedoraproject.org/prod/streams/next/builds/40.20240808.1.0/aarch64/fedora-coreos-40.20240808.1.0-aws.aarch64.vmdk.xz.sig",
                                "sha256": "e2debe38ca40ff1fd1e120fd8d2e47b9382aa7feca4a0f0c478581e1d69e0e28",
                                "uncompressed-sha256": "a20f86986c27ad9d81a5871e99775a4f52de6d380b452aa72513b44bf340ec47"
                            }
                        }
                    }
                },
                "azure": {
                    "release": "40.20240808.1.0",
                    "formats": {
                        "vhd.xz": {
                            "disk": {
                                "location": "https://builds.coreos.fedoraproject.org/prod/streams/next/builds/40.20240808.1.0/aarch64/fedora-coreos-40.20240808.1.0-azure.aarch64.vhd.xz",
                                "signature": "https://builds.coreos.fedoraproject.org/prod/streams/next/builds/40.20240808.1.0/aarch64/fedora-coreos-40.20240808.1.0-azure.aarch64.vhd.xz.sig",
                                "sha256": "8423e277f5b24db80c1088a4011bd041f66e0725a15a1d6e088b3df7c3570d3c",
                                "uncompressed-sha256": "67e40c74db2b4c5c750d0588d19d842bc4a69ea3ac8e54860798caf33e23923d"
                            }
                        }
                    }
                },
                "gcp": {
                    "release": "40.20240808.1.0",
                    "formats": {
                        "tar.gz": {
                            "disk": {
                                "location": "https://builds.coreos.fedoraproject.org/prod/streams/next/builds/40.20240808.1.0/aarch64/fedora-coreos-40.20240808.1.0-gcp.aarch64.tar.gz",
                                "signature": "https://builds.coreos.fedoraproject.org/prod/streams/next/builds/40.20240808.1.0/aarch64/fedora-coreos-40.20240808.1.0-gcp.aarch64.tar.gz.sig",
                                "sha256": "626c4b1ca469e04ba531febb6d3aeea4a771b4b4d772cacc900a857dc6f91459",
                                "uncompressed-sha256": "1846a27e1f4bc70fb9e2febddd87799c0f2c972eb2c19017801ca1c45d10efe5"
                            }
                        }
                    }
                },
                "hyperv": {
                    "release": "40.20240808.1.0",
                    "formats": {
                        "vhdx.zip": {
                            "disk": {
                                "location": "https://builds.coreos.fedoraproject.org/prod/streams/next/builds/40.20240808.1.0/aarch64/fedora-coreos-40.20240808.1.0-hyperv.aarch64.vhdx.zip",
                                "signature": "https://builds.coreos.fedoraproject.org/prod/streams/next/builds/40.20240808.1.0/aarch64/fedora-coreos-40.20240808.1.0-hyperv.aarch64.vhdx.zip.sig",
                                "sha256": "1ca8fd9c6912007c8c6183d97a6bb00c6273949850ce83863609a7860b8ababf",
                                "uncompressed-sha256": "831a206f97be04df6c3a078556ee85a4c5e1833905b87504836a58b24c55f96c"
                            }
                        }
                    }
                },
                "metal": {
                    "release": "40.20240808.1.0",
                    "formats": {
                        "4k.raw.xz": {
                            "disk": {
                                "location": "https://builds.coreos.fedoraproject.org/prod/streams/next/builds/40.20240808.1.0/aarch64/fedora-coreos-40.20240808.1.0-metal4k.aarch64.raw.xz",
                                "signature": "https://builds.coreos.fedoraproject.org/prod/streams/next/builds/40.20240808.1.0/aarch64/fedora-coreos-40.20240808.1.0-metal4k.aarch64.raw.xz.sig",
                                "sha256": "6d334bf8b16d6d6a0933d6087e4a94411d36d2ae8aaec80ca6472e657ecca02f",
                                "uncompressed-sha256": "81991b8aaa8a78bdcb0287a8874e07e484dd4bf4c5b2971be1a2cef673ab7ee1"
                            }
                        },
                        "iso": {
                            "disk": {
                                "location": "https://builds.coreos.fedoraproject.org/prod/streams/next/builds/40.20240808.1.0/aarch64/fedora-coreos-40.20240808.1.0-live.aarch64.iso",
                                "signature": "https://builds.coreos.fedoraproject.org/prod/streams/next/builds/40.20240808.1.0/aarch64/fedora-coreos-40.20240808.1.0-live.aarch64.iso.sig",
                                "sha256": "a9e584937dc56e9544291b02fff06a6d4f01a9c78e1ae560eefe338d43ff1f04"
                            }
                        },
                        "pxe": {
                            "kernel": {
                                "location": "https://builds.coreos.fedoraproject.org/prod/streams/next/builds/40.20240808.1.0/aarch64/fedora-coreos-40.20240808.1.0-live-kernel-aarch64",
                                "signature": "https://builds.coreos.fedoraproject.org/prod/streams/next/builds/40.20240808.1.0/aarch64/fedora-coreos-40.20240808.1.0-live-kernel-aarch64.sig",
                                "sha256": "cb0b0862cd36bb3accca36434076086a1a72059498c1fd320361c08d8255c7dd"
                            },
                            "initramfs": {
                                "location": "https://builds.coreos.fedoraproject.org/prod/streams/next/builds/40.20240808.1.0/aarch64/fedora-coreos-40.20240808.1.0-live-initramfs.aarch64.img",
                                "signature": "https://builds.coreos.fedoraproject.org/prod/streams/next/builds/40.20240808.1.0/aarch64/fedora-coreos-40.20240808.1.0-live-initramfs.aarch64.img.sig",
                                "sha256": "2f06b8df6443ed7b0a923b1466076c122fa29d2592f191e8f14286e6857b886b"
                            },
                            "rootfs": {
                                "location": "https://builds.coreos.fedoraproject.org/prod/streams/next/builds/40.20240808.1.0/aarch64/fedora-coreos-40.20240808.1.0-live-rootfs.aarch64.img",
                                "signature": "https://builds.coreos.fedoraproject.org/prod/streams/next/builds/40.20240808.1.0/aarch64/fedora-coreos-40.20240808.1.0-live-rootfs.aarch64.img.sig",
                                "sha256": "901df33fd3aab32c0bdf4dbd9da36edf91160e24845674f0d424df24adea24ed"
                            }
                        },
                        "raw.xz": {
                            "disk": {
                                "location": "https://builds.coreos.fedoraproject.org/prod/streams/next/builds/40.20240808.1.0/aarch64/fedora-coreos-40.20240808.1.0-metal.aarch64.raw.xz",
                                "signature": "https://builds.coreos.fedoraproject.org/prod/streams/next/builds/40.20240808.1.0/aarch64/fedora-coreos-40.20240808.1.0-metal.aarch64.raw.xz.sig",
                                "sha256": "123a613e516b5c749a92471cc6d63f9d1f5a20a8f1dc83d4f95fce33a6a29804",
                                "uncompressed-sha256": "0dc5a1c588b5bdf96e2bbefeb34d7e57626ba5635b61ebeee1b85e889d50a15e"
                            }
                        }
                    }
                },
                "openstack": {
                    "release": "40.20240808.1.0",
                    "formats": {
                        "qcow2.xz": {
                            "disk": {
                                "location": "https://builds.coreos.fedoraproject.org/prod/streams/next/builds/40.20240808.1.0/aarch64/fedora-coreos-40.20240808.1.0-openstack.aarch64.qcow2.xz",
                                "signature": "https://builds.coreos.fedoraproject.org/prod/streams/next/builds/40.20240808.1.0/aarch64/fedora-coreos-40.20240808.1.0-openstack.aarch64.qcow2.xz.sig",
                                "sha256": "6701fde949677d6a5173b1e134f994c9c3f179002a152bb4bfb9bfb4968fde2e",
                                "uncompressed-sha256": "0ae6c3fe4894766d685333163b3434a069a72a9b28a00c4c39dcb2716ea38932"
                            }
                        }
                    }
                },
                "qemu": {
                    "release": "40.20240808.1.0",
                    "formats": {
                        "qcow2.xz": {
                            "disk": {
                                "location": "https://builds.coreos.fedoraproject.org/prod/streams/next/builds/40.20240808.1.0/aarch64/fedora-coreos-40.20240808.1.0-qemu.aarch64.qcow2.xz",
                                "signature": "https://builds.coreos.fedoraproject.org/prod/streams/next/builds/40.20240808.1.0/aarch64/fedora-coreos-40.20240808.1.0-qemu.aarch64.qcow2.xz.sig",
                                "sha256": "2cb6bdcb5c6b78ddf85449bd399156ec8c6605b8eee5fae33c78aeb63144451c",
                                "uncompressed-sha256": "390b324bc808c5d4be0cf7928f42b50591e9758be70b23ff013f1eca2b993cb8"
                            }
                        }
                    }
                }
            },
            "images": {
                "aws": {
                    "regions": {
                        "af-south-1": {
                            "release": "40.20240808.1.0",
                            "image": "ami-09b60426b853b5b0a"
                        },
                        "ap-east-1": {
                            "release": "40.20240808.1.0",
                            "image": "ami-0f99fb68fe3877a1b"
                        },
                        "ap-northeast-1": {
                            "release": "40.20240808.1.0",
                            "image": "ami-085e0d5f85e21b912"
                        },
                        "ap-northeast-2": {
                            "release": "40.20240808.1.0",
                            "image": "ami-0d0abf2e0a3ffcaf5"
                        },
                        "ap-northeast-3": {
                            "release": "40.20240808.1.0",
                            "image": "ami-08ac5a17332cd1c75"
                        },
                        "ap-south-1": {
                            "release": "40.20240808.1.0",
                            "image": "ami-0a33dea0d053d45c0"
                        },
                        "ap-south-2": {
                            "release": "40.20240808.1.0",
                            "image": "ami-0074fa1fe0798fb20"
                        },
                        "ap-southeast-1": {
                            "release": "40.20240808.1.0",
                            "image": "ami-0f2718f653c5714e2"
                        },
                        "ap-southeast-2": {
                            "release": "40.20240808.1.0",
                            "image": "ami-019f2588f4dd29977"
                        },
                        "ap-southeast-3": {
                            "release": "40.20240808.1.0",
                            "image": "ami-0ffb741e5ee2eeba2"
                        },
                        "ap-southeast-4": {
                            "release": "40.20240808.1.0",
                            "image": "ami-00b0344bcac848ec9"
                        },
                        "ca-central-1": {
                            "release": "40.20240808.1.0",
                            "image": "ami-005292a62b438b623"
                        },
                        "ca-west-1": {
                            "release": "40.20240808.1.0",
                            "image": "ami-0207f657da0f1da71"
                        },
                        "eu-central-1": {
                            "release": "40.20240808.1.0",
                            "image": "ami-0cea8713794886afd"
                        },
                        "eu-central-2": {
                            "release": "40.20240808.1.0",
                            "image": "ami-02906a43e9568def9"
                        },
                        "eu-north-1": {
                            "release": "40.20240808.1.0",
                            "image": "ami-03513fc216cea4491"
                        },
                        "eu-south-1": {
                            "release": "40.20240808.1.0",
                            "image": "ami-090bd7a4dd0692121"
                        },
                        "eu-south-2": {
                            "release": "40.20240808.1.0",
                            "image": "ami-03dc8c171ea10a92d"
                        },
                        "eu-west-1": {
                            "release": "40.20240808.1.0",
                            "image": "ami-07f5cc9d165e44b1a"
                        },
                        "eu-west-2": {
                            "release": "40.20240808.1.0",
                            "image": "ami-0d773619c7ac118da"
                        },
                        "eu-west-3": {
                            "release": "40.20240808.1.0",
                            "image": "ami-019ea313d46ef8299"
                        },
                        "il-central-1": {
                            "release": "40.20240808.1.0",
                            "image": "ami-0b2581dfecb6d90a3"
                        },
                        "me-central-1": {
                            "release": "40.20240808.1.0",
                            "image": "ami-00c02c0ca987dcf11"
                        },
                        "me-south-1": {
                            "release": "40.20240808.1.0",
                            "image": "ami-0cf06b6664f2d604f"
                        },
                        "sa-east-1": {
                            "release": "40.20240808.1.0",
                            "image": "ami-073c23a34ad061b3a"
                        },
                        "us-east-1": {
                            "release": "40.20240808.1.0",
                            "image": "ami-07d517522eaa378bd"
                        },
                        "us-east-2": {
                            "release": "40.20240808.1.0",
                            "image": "ami-0742710ff63e3a161"
                        },
                        "us-west-1": {
                            "release": "40.20240808.1.0",
                            "image": "ami-0628fba2c8b408354"
                        },
                        "us-west-2": {
                            "release": "40.20240808.1.0",
                            "image": "ami-0268fac848ab25bc9"
                        }
                    }
                },
                "gcp": {
                    "release": "40.20240808.1.0",
                    "project": "fedora-coreos-cloud",
                    "family": "fedora-coreos-next-arm64",
                    "name": "fedora-coreos-40-20240808-1-0-gcp-aarch64"
                }
            }
        },
        "ppc64le": {
            "artifacts": {
                "metal": {
                    "release": "40.20240808.1.0",
                    "formats": {
                        "4k.raw.xz": {
                            "disk": {
                                "location": "https://builds.coreos.fedoraproject.org/prod/streams/next/builds/40.20240808.1.0/ppc64le/fedora-coreos-40.20240808.1.0-metal4k.ppc64le.raw.xz",
                                "signature": "https://builds.coreos.fedoraproject.org/prod/streams/next/builds/40.20240808.1.0/ppc64le/fedora-coreos-40.20240808.1.0-metal4k.ppc64le.raw.xz.sig",
                                "sha256": "081cf40bcf3d588abcfdde34e75ec104c835e7b0d5d67f62335a9881eedf4fc4",
                                "uncompressed-sha256": "c2d2d4de58c876d0b5ec49153e16412c0bbc13aa66452ea198981f0f98deaaea"
                            }
                        },
                        "iso": {
                            "disk": {
                                "location": "https://builds.coreos.fedoraproject.org/prod/streams/next/builds/40.20240808.1.0/ppc64le/fedora-coreos-40.20240808.1.0-live.ppc64le.iso",
                                "signature": "https://builds.coreos.fedoraproject.org/prod/streams/next/builds/40.20240808.1.0/ppc64le/fedora-coreos-40.20240808.1.0-live.ppc64le.iso.sig",
                                "sha256": "15e4578bb35924379e1322a2c16bc5ca8eb0ab42976904d285a0198e1f9a3188"
                            }
                        },
                        "pxe": {
                            "kernel": {
                                "location": "https://builds.coreos.fedoraproject.org/prod/streams/next/builds/40.20240808.1.0/ppc64le/fedora-coreos-40.20240808.1.0-live-kernel-ppc64le",
                                "signature": "https://builds.coreos.fedoraproject.org/prod/streams/next/builds/40.20240808.1.0/ppc64le/fedora-coreos-40.20240808.1.0-live-kernel-ppc64le.sig",
                                "sha256": "c9e2f1cb0a59a1d1b74e256e4f74078eb099e998df7c48b2e15cefc63944f92a"
                            },
                            "initramfs": {
                                "location": "https://builds.coreos.fedoraproject.org/prod/streams/next/builds/40.20240808.1.0/ppc64le/fedora-coreos-40.20240808.1.0-live-initramfs.ppc64le.img",
                                "signature": "https://builds.coreos.fedoraproject.org/prod/streams/next/builds/40.20240808.1.0/ppc64le/fedora-coreos-40.20240808.1.0-live-initramfs.ppc64le.img.sig",
                                "sha256": "0f5468354ff29176f6e617cfc139e538b12f90994574c54539ecbb545cde3c9a"
                            },
                            "rootfs": {
                                "location": "https://builds.coreos.fedoraproject.org/prod/streams/next/builds/40.20240808.1.0/ppc64le/fedora-coreos-40.20240808.1.0-live-rootfs.ppc64le.img",
                                "signature": "https://builds.coreos.fedoraproject.org/prod/streams/next/builds/40.20240808.1.0/ppc64le/fedora-coreos-40.20240808.1.0-live-rootfs.ppc64le.img.sig",
                                "sha256": "200787cb559ba80452d91bf9b933e5036df15fd5ba02020d31fcb61200779ebf"
                            }
                        },
                        "raw.xz": {
                            "disk": {
                                "location": "https://builds.coreos.fedoraproject.org/prod/streams/next/builds/40.20240808.1.0/ppc64le/fedora-coreos-40.20240808.1.0-metal.ppc64le.raw.xz",
                                "signature": "https://builds.coreos.fedoraproject.org/prod/streams/next/builds/40.20240808.1.0/ppc64le/fedora-coreos-40.20240808.1.0-metal.ppc64le.raw.xz.sig",
                                "sha256": "4f026d0ee49cd75f66fcb057725d17d5fbe2da5dd419997bc2328abd13f4c24d",
                                "uncompressed-sha256": "f40a1383f7ad78e0c306dbe06470df0659fe8fd6db507cd284db9b205c457790"
                            }
                        }
                    }
                },
                "openstack": {
                    "release": "40.20240808.1.0",
                    "formats": {
                        "qcow2.xz": {
                            "disk": {
                                "location": "https://builds.coreos.fedoraproject.org/prod/streams/next/builds/40.20240808.1.0/ppc64le/fedora-coreos-40.20240808.1.0-openstack.ppc64le.qcow2.xz",
                                "signature": "https://builds.coreos.fedoraproject.org/prod/streams/next/builds/40.20240808.1.0/ppc64le/fedora-coreos-40.20240808.1.0-openstack.ppc64le.qcow2.xz.sig",
                                "sha256": "03bcc27eee9848713362aafb7d5fe2756569247fb80b948a9e958bfbfbf334aa",
                                "uncompressed-sha256": "ba94c019c7072020ced94582b634d296429f116d11fc5cab78a0b9c9919fdaab"
                            }
                        }
                    }
                },
                "powervs": {
                    "release": "40.20240808.1.0",
                    "formats": {
                        "ova.gz": {
                            "disk": {
                                "location": "https://builds.coreos.fedoraproject.org/prod/streams/next/builds/40.20240808.1.0/ppc64le/fedora-coreos-40.20240808.1.0-powervs.ppc64le.ova.gz",
                                "signature": "https://builds.coreos.fedoraproject.org/prod/streams/next/builds/40.20240808.1.0/ppc64le/fedora-coreos-40.20240808.1.0-powervs.ppc64le.ova.gz.sig",
                                "sha256": "966f68883ab168dd73b935560cf6bca6c16bcd3883b4363269d4926524d5d20f",
                                "uncompressed-sha256": "f6d6271b335a6494b9ef42c0511d4066d989c0a48033a72900d2a522d9ec7bf0"
                            }
                        }
                    }
                },
                "qemu": {
                    "release": "40.20240808.1.0",
                    "formats": {
                        "qcow2.xz": {
                            "disk": {
                                "location": "https://builds.coreos.fedoraproject.org/prod/streams/next/builds/40.20240808.1.0/ppc64le/fedora-coreos-40.20240808.1.0-qemu.ppc64le.qcow2.xz",
                                "signature": "https://builds.coreos.fedoraproject.org/prod/streams/next/builds/40.20240808.1.0/ppc64le/fedora-coreos-40.20240808.1.0-qemu.ppc64le.qcow2.xz.sig",
                                "sha256": "30f476e597d518b96eb65570cb52f6ad7030c56fa28959cd6c3e944ca1349ab9",
                                "uncompressed-sha256": "b01e9d808abaf3155ae43be2f9f0202ffee2f86e73083476a6a701e412b263a6"
                            }
                        }
                    }
                }
            },
            "images": {}
        },
        "s390x": {
            "artifacts": {
                "ibmcloud": {
                    "release": "40.20240808.1.0",
                    "formats": {
                        "qcow2.xz": {
                            "disk": {
                                "location": "https://builds.coreos.fedoraproject.org/prod/streams/next/builds/40.20240808.1.0/s390x/fedora-coreos-40.20240808.1.0-ibmcloud.s390x.qcow2.xz",
                                "signature": "https://builds.coreos.fedoraproject.org/prod/streams/next/builds/40.20240808.1.0/s390x/fedora-coreos-40.20240808.1.0-ibmcloud.s390x.qcow2.xz.sig",
                                "sha256": "941e51a78640340a21413ef05d42975507f8cc87de89d53f33bca85a6be3c734",
                                "uncompressed-sha256": "aef42eecd9cb084c078023f26eee10debde0442046a6809fb09d4bfa9ef1933f"
                            }
                        }
                    }
                },
                "metal": {
                    "release": "40.20240808.1.0",
                    "formats": {
                        "4k.raw.xz": {
                            "disk": {
                                "location": "https://builds.coreos.fedoraproject.org/prod/streams/next/builds/40.20240808.1.0/s390x/fedora-coreos-40.20240808.1.0-metal4k.s390x.raw.xz",
                                "signature": "https://builds.coreos.fedoraproject.org/prod/streams/next/builds/40.20240808.1.0/s390x/fedora-coreos-40.20240808.1.0-metal4k.s390x.raw.xz.sig",
                                "sha256": "aea8a38c49817dfabcd6efc681434e30707363ecf8b61a3642713f25acedbb78",
                                "uncompressed-sha256": "8c8dad09ad391d832a0ee2270875bc6fd9ad323fed995da5af7dd74a312636b0"
                            }
                        },
                        "iso": {
                            "disk": {
                                "location": "https://builds.coreos.fedoraproject.org/prod/streams/next/builds/40.20240808.1.0/s390x/fedora-coreos-40.20240808.1.0-live.s390x.iso",
                                "signature": "https://builds.coreos.fedoraproject.org/prod/streams/next/builds/40.20240808.1.0/s390x/fedora-coreos-40.20240808.1.0-live.s390x.iso.sig",
                                "sha256": "d4267f9ed99d71fdc8adba84018ac4d528ae1079c01c8d86a5bf73c121d976f1"
                            }
                        },
                        "pxe": {
                            "kernel": {
                                "location": "https://builds.coreos.fedoraproject.org/prod/streams/next/builds/40.20240808.1.0/s390x/fedora-coreos-40.20240808.1.0-live-kernel-s390x",
                                "signature": "https://builds.coreos.fedoraproject.org/prod/streams/next/builds/40.20240808.1.0/s390x/fedora-coreos-40.20240808.1.0-live-kernel-s390x.sig",
                                "sha256": "cd0ccb133703f0b51afea4a2bb0c1e76111a442745137e866f0945f808191a7f"
                            },
                            "initramfs": {
                                "location": "https://builds.coreos.fedoraproject.org/prod/streams/next/builds/40.20240808.1.0/s390x/fedora-coreos-40.20240808.1.0-live-initramfs.s390x.img",
                                "signature": "https://builds.coreos.fedoraproject.org/prod/streams/next/builds/40.20240808.1.0/s390x/fedora-coreos-40.20240808.1.0-live-initramfs.s390x.img.sig",
                                "sha256": "e0eb5b9f4bf9fec51c1379b4d5c03691d5a9cda943afc652a9a42b8801113a69"
                            },
                            "rootfs": {
                                "location": "https://builds.coreos.fedoraproject.org/prod/streams/next/builds/40.20240808.1.0/s390x/fedora-coreos-40.20240808.1.0-live-rootfs.s390x.img",
                                "signature": "https://builds.coreos.fedoraproject.org/prod/streams/next/builds/40.20240808.1.0/s390x/fedora-coreos-40.20240808.1.0-live-rootfs.s390x.img.sig",
                                "sha256": "77c8d315def8b8446d10c53c2294c8784d924ae0c5bfe65dd1cb0d3e7b1b763a"
                            }
                        },
                        "raw.xz": {
                            "disk": {
                                "location": "https://builds.coreos.fedoraproject.org/prod/streams/next/builds/40.20240808.1.0/s390x/fedora-coreos-40.20240808.1.0-metal.s390x.raw.xz",
                                "signature": "https://builds.coreos.fedoraproject.org/prod/streams/next/builds/40.20240808.1.0/s390x/fedora-coreos-40.20240808.1.0-metal.s390x.raw.xz.sig",
                                "sha256": "d40ea9a950c2d80117c05b751a6cd3135dced74e2a6cd5d0cabee13998112f5a",
                                "uncompressed-sha256": "5642f8b4d3bc0af7c242261412040ab1429f4378e686b587d918f9d0f9d7b2a8"
                            }
                        }
                    }
                },
                "openstack": {
                    "release": "40.20240808.1.0",
                    "formats": {
                        "qcow2.xz": {
                            "disk": {
                                "location": "https://builds.coreos.fedoraproject.org/prod/streams/next/builds/40.20240808.1.0/s390x/fedora-coreos-40.20240808.1.0-openstack.s390x.qcow2.xz",
                                "signature": "https://builds.coreos.fedoraproject.org/prod/streams/next/builds/40.20240808.1.0/s390x/fedora-coreos-40.20240808.1.0-openstack.s390x.qcow2.xz.sig",
                                "sha256": "4874cd017914ebc8466b01502bec801b55b5f44c7344894ac66f3f6c244cc1b3",
                                "uncompressed-sha256": "9d8b59da2729a3b9f03b49086585821325008b73c47ac4fb8bbe91e3205f36c1"
                            }
                        }
                    }
                },
                "qemu": {
                    "release": "40.20240808.1.0",
                    "formats": {
                        "qcow2.xz": {
                            "disk": {
                                "location": "https://builds.coreos.fedoraproject.org/prod/streams/next/builds/40.20240808.1.0/s390x/fedora-coreos-40.20240808.1.0-qemu.s390x.qcow2.xz",
                                "signature": "https://builds.coreos.fedoraproject.org/prod/streams/next/builds/40.20240808.1.0/s390x/fedora-coreos-40.20240808.1.0-qemu.s390x.qcow2.xz.sig",
                                "sha256": "3044309acc991a48bb8192b6effde193b1837e57fd48eaafa2b2198daab006d2",
                                "uncompressed-sha256": "482e0c2ec60888722d2b195b9c0aceebc0da8abdd11b6258adde6eedc95c8ebc"
                            }
                        }
                    }
                }
            },
            "images": {}
        },
        "x86_64": {
            "artifacts": {
                "aliyun": {
                    "release": "40.20240808.1.0",
                    "formats": {
                        "qcow2.xz": {
                            "disk": {
                                "location": "https://builds.coreos.fedoraproject.org/prod/streams/next/builds/40.20240808.1.0/x86_64/fedora-coreos-40.20240808.1.0-aliyun.x86_64.qcow2.xz",
                                "signature": "https://builds.coreos.fedoraproject.org/prod/streams/next/builds/40.20240808.1.0/x86_64/fedora-coreos-40.20240808.1.0-aliyun.x86_64.qcow2.xz.sig",
                                "sha256": "5606b33b4687baaf8ade31b77d2cbe191f8a624239e453bf3fccd098ded9169c",
                                "uncompressed-sha256": "95e42181e7d08b3e05e40c5fa9284c1c74d950c8bfc6250079958452afb5b300"
                            }
                        }
                    }
                },
                "applehv": {
                    "release": "40.20240808.1.0",
                    "formats": {
                        "raw.gz": {
                            "disk": {
                                "location": "https://builds.coreos.fedoraproject.org/prod/streams/next/builds/40.20240808.1.0/x86_64/fedora-coreos-40.20240808.1.0-applehv.x86_64.raw.gz",
                                "signature": "https://builds.coreos.fedoraproject.org/prod/streams/next/builds/40.20240808.1.0/x86_64/fedora-coreos-40.20240808.1.0-applehv.x86_64.raw.gz.sig",
                                "sha256": "7da4df0a83e4880f21cc30782966917103ca2b51a78f959f4acab8e2b9ed799a",
                                "uncompressed-sha256": "2fe6abe2ca6a629a1100de372ab730d040986286f38d37f3044033c47108cb43"
                            }
                        }
                    }
                },
                "aws": {
                    "release": "40.20240808.1.0",
                    "formats": {
                        "vmdk.xz": {
                            "disk": {
                                "location": "https://builds.coreos.fedoraproject.org/prod/streams/next/builds/40.20240808.1.0/x86_64/fedora-coreos-40.20240808.1.0-aws.x86_64.vmdk.xz",
                                "signature": "https://builds.coreos.fedoraproject.org/prod/streams/next/builds/40.20240808.1.0/x86_64/fedora-coreos-40.20240808.1.0-aws.x86_64.vmdk.xz.sig",
                                "sha256": "4ddfa2aaa6aa623798c69b3772788de64005d33f9840b3072efe9e24af4f30e4",
                                "uncompressed-sha256": "3a4dff25d12702f6d3813c2f822f0df0e402d0cb0e0714c516c0db8f9fb2f02d"
                            }
                        }
                    }
                },
                "azure": {
                    "release": "40.20240808.1.0",
                    "formats": {
                        "vhd.xz": {
                            "disk": {
                                "location": "https://builds.coreos.fedoraproject.org/prod/streams/next/builds/40.20240808.1.0/x86_64/fedora-coreos-40.20240808.1.0-azure.x86_64.vhd.xz",
                                "signature": "https://builds.coreos.fedoraproject.org/prod/streams/next/builds/40.20240808.1.0/x86_64/fedora-coreos-40.20240808.1.0-azure.x86_64.vhd.xz.sig",
                                "sha256": "62174ef36de9110bdeefd80675b4dc54d729d0ec82620b02cc28b8b56f49a301",
                                "uncompressed-sha256": "bb8e8ad6f8ae6f10d70cb92b698e828f0e42985ba2e748cbdaf1252edaa31a8b"
                            }
                        }
                    }
                },
                "azurestack": {
                    "release": "40.20240808.1.0",
                    "formats": {
                        "vhd.xz": {
                            "disk": {
                                "location": "https://builds.coreos.fedoraproject.org/prod/streams/next/builds/40.20240808.1.0/x86_64/fedora-coreos-40.20240808.1.0-azurestack.x86_64.vhd.xz",
                                "signature": "https://builds.coreos.fedoraproject.org/prod/streams/next/builds/40.20240808.1.0/x86_64/fedora-coreos-40.20240808.1.0-azurestack.x86_64.vhd.xz.sig",
                                "sha256": "a0dd1a4b8e81cd352775f447e9c61b5d3f5396d5a22f6ba5893a6c7ee3196068",
                                "uncompressed-sha256": "70b79613f0133fb10daa4fba08ba30eada9024b50f7df0a29a74569b4e99354d"
                            }
                        }
                    }
                },
                "digitalocean": {
                    "release": "40.20240808.1.0",
                    "formats": {
                        "qcow2.gz": {
                            "disk": {
                                "location": "https://builds.coreos.fedoraproject.org/prod/streams/next/builds/40.20240808.1.0/x86_64/fedora-coreos-40.20240808.1.0-digitalocean.x86_64.qcow2.gz",
                                "signature": "https://builds.coreos.fedoraproject.org/prod/streams/next/builds/40.20240808.1.0/x86_64/fedora-coreos-40.20240808.1.0-digitalocean.x86_64.qcow2.gz.sig",
                                "sha256": "1b0a16945b2a0166a9a7c289d216aba2cc1239e120ff3adb86b50ab355c7fbf3",
                                "uncompressed-sha256": "151caa0f99140ab0b27288b2e0e7743511dcfc22c5482c1a44e0e90a0076fbf2"
                            }
                        }
                    }
                },
                "exoscale": {
                    "release": "40.20240808.1.0",
                    "formats": {
                        "qcow2.xz": {
                            "disk": {
                                "location": "https://builds.coreos.fedoraproject.org/prod/streams/next/builds/40.20240808.1.0/x86_64/fedora-coreos-40.20240808.1.0-exoscale.x86_64.qcow2.xz",
                                "signature": "https://builds.coreos.fedoraproject.org/prod/streams/next/builds/40.20240808.1.0/x86_64/fedora-coreos-40.20240808.1.0-exoscale.x86_64.qcow2.xz.sig",
                                "sha256": "6c2300368880814068777d5a0ef33bc44a734dcbff1eebc20a0b989c2151007d",
                                "uncompressed-sha256": "bb00774d310cfe5c82feca3a82d284ac399c4882b7dee1867851c490be33eaf5"
                            }
                        }
                    }
                },
                "gcp": {
                    "release": "40.20240808.1.0",
                    "formats": {
                        "tar.gz": {
                            "disk": {
                                "location": "https://builds.coreos.fedoraproject.org/prod/streams/next/builds/40.20240808.1.0/x86_64/fedora-coreos-40.20240808.1.0-gcp.x86_64.tar.gz",
                                "signature": "https://builds.coreos.fedoraproject.org/prod/streams/next/builds/40.20240808.1.0/x86_64/fedora-coreos-40.20240808.1.0-gcp.x86_64.tar.gz.sig",
                                "sha256": "57c117ad77b091da13fa7af9c24427939c409b5823ea6a90abf45040c8c397b1",
                                "uncompressed-sha256": "22e67881971c890780046ed2b02871c26dcdeca8947d39db2b9a4b58032532dd"
                            }
                        }
                    }
                },
                "hyperv": {
                    "release": "40.20240808.1.0",
                    "formats": {
                        "vhdx.zip": {
                            "disk": {
                                "location": "https://builds.coreos.fedoraproject.org/prod/streams/next/builds/40.20240808.1.0/x86_64/fedora-coreos-40.20240808.1.0-hyperv.x86_64.vhdx.zip",
                                "signature": "https://builds.coreos.fedoraproject.org/prod/streams/next/builds/40.20240808.1.0/x86_64/fedora-coreos-40.20240808.1.0-hyperv.x86_64.vhdx.zip.sig",
                                "sha256": "c068ab71738f2cb855fef0cb3a932f2108c2becaa25621032ec5c375b99cfb24",
                                "uncompressed-sha256": "d6b86b2dbcd86ca1f4805628fc37f5d00ef067362ffb8bb7f131f52ff78d30b3"
                            }
                        }
                    }
                },
                "ibmcloud": {
                    "release": "40.20240808.1.0",
                    "formats": {
                        "qcow2.xz": {
                            "disk": {
                                "location": "https://builds.coreos.fedoraproject.org/prod/streams/next/builds/40.20240808.1.0/x86_64/fedora-coreos-40.20240808.1.0-ibmcloud.x86_64.qcow2.xz",
                                "signature": "https://builds.coreos.fedoraproject.org/prod/streams/next/builds/40.20240808.1.0/x86_64/fedora-coreos-40.20240808.1.0-ibmcloud.x86_64.qcow2.xz.sig",
                                "sha256": "46fb973e324c3f7dae74155e8f2cd9e7171715edeb010cdcf4117829a86b537c",
                                "uncompressed-sha256": "0e081d291862ce3e84a18a49cf77893dfb7bf6ca290b0399120c45c6fa771924"
                            }
                        }
                    }
                },
                "kubevirt": {
                    "release": "40.20240808.1.0",
                    "formats": {
                        "ociarchive": {
                            "disk": {
                                "location": "https://builds.coreos.fedoraproject.org/prod/streams/next/builds/40.20240808.1.0/x86_64/fedora-coreos-40.20240808.1.0-kubevirt.x86_64.ociarchive",
                                "signature": "https://builds.coreos.fedoraproject.org/prod/streams/next/builds/40.20240808.1.0/x86_64/fedora-coreos-40.20240808.1.0-kubevirt.x86_64.ociarchive.sig",
                                "sha256": "b81a8c16471c72abf60e7fa66fe69e482db6f0effa4c1b27e6f62707ee04f9cf"
                            }
                        }
                    }
                },
                "metal": {
                    "release": "40.20240808.1.0",
                    "formats": {
                        "4k.raw.xz": {
                            "disk": {
                                "location": "https://builds.coreos.fedoraproject.org/prod/streams/next/builds/40.20240808.1.0/x86_64/fedora-coreos-40.20240808.1.0-metal4k.x86_64.raw.xz",
                                "signature": "https://builds.coreos.fedoraproject.org/prod/streams/next/builds/40.20240808.1.0/x86_64/fedora-coreos-40.20240808.1.0-metal4k.x86_64.raw.xz.sig",
                                "sha256": "0068a4774c3a25a41cc90c9e7edaee994aa69a851252bd9a9c070d0780780efb",
                                "uncompressed-sha256": "ff994ceff1281133c460933a96e86deb5798414c722060aa3b3b3f1b506824f2"
                            }
                        },
                        "iso": {
                            "disk": {
                                "location": "https://builds.coreos.fedoraproject.org/prod/streams/next/builds/40.20240808.1.0/x86_64/fedora-coreos-40.20240808.1.0-live.x86_64.iso",
                                "signature": "https://builds.coreos.fedoraproject.org/prod/streams/next/builds/40.20240808.1.0/x86_64/fedora-coreos-40.20240808.1.0-live.x86_64.iso.sig",
                                "sha256": "7cf84e0e4de57b7a43169318288725b277be803baf48f37085db3d6960c1759f"
                            }
                        },
                        "pxe": {
                            "kernel": {
                                "location": "https://builds.coreos.fedoraproject.org/prod/streams/next/builds/40.20240808.1.0/x86_64/fedora-coreos-40.20240808.1.0-live-kernel-x86_64",
                                "signature": "https://builds.coreos.fedoraproject.org/prod/streams/next/builds/40.20240808.1.0/x86_64/fedora-coreos-40.20240808.1.0-live-kernel-x86_64.sig",
                                "sha256": "36eac90bbc9b6c594515fa36e2dfd4e15b769bbb5015f3b024d7bde4c4f50abf"
                            },
                            "initramfs": {
                                "location": "https://builds.coreos.fedoraproject.org/prod/streams/next/builds/40.20240808.1.0/x86_64/fedora-coreos-40.20240808.1.0-live-initramfs.x86_64.img",
                                "signature": "https://builds.coreos.fedoraproject.org/prod/streams/next/builds/40.20240808.1.0/x86_64/fedora-coreos-40.20240808.1.0-live-initramfs.x86_64.img.sig",
                                "sha256": "3600e5f79d0ecd85f0809094e9443166e1599f86924781583a15060ba58840bb"
                            },
                            "rootfs": {
                                "location": "https://builds.coreos.fedoraproject.org/prod/streams/next/builds/40.20240808.1.0/x86_64/fedora-coreos-40.20240808.1.0-live-rootfs.x86_64.img",
                                "signature": "https://builds.coreos.fedoraproject.org/prod/streams/next/builds/40.20240808.1.0/x86_64/fedora-coreos-40.20240808.1.0-live-rootfs.x86_64.img.sig",
                                "sha256": "25f6dfd17195ebe204fcecac4abf3af4b1e72a025d29f9d64f0483bdb088a203"
                            }
                        },
                        "raw.xz": {
                            "disk": {
                                "location": "https://builds.coreos.fedoraproject.org/prod/streams/next/builds/40.20240808.1.0/x86_64/fedora-coreos-40.20240808.1.0-metal.x86_64.raw.xz",
                                "signature": "https://builds.coreos.fedoraproject.org/prod/streams/next/builds/40.20240808.1.0/x86_64/fedora-coreos-40.20240808.1.0-metal.x86_64.raw.xz.sig",
                                "sha256": "a8956b340af03d54664b022f2c994bbc7d82e352aa1b9300d9831344a4aed08e",
                                "uncompressed-sha256": "ed86f37ff91e7b5f833b9dd972dddd415a25d6141acc56346dd360b8e524a19f"
                            }
                        }
                    }
                },
                "nutanix": {
                    "release": "40.20240808.1.0",
                    "formats": {
                        "qcow2": {
                            "disk": {
                                "location": "https://builds.coreos.fedoraproject.org/prod/streams/next/builds/40.20240808.1.0/x86_64/fedora-coreos-40.20240808.1.0-nutanix.x86_64.qcow2",
                                "signature": "https://builds.coreos.fedoraproject.org/prod/streams/next/builds/40.20240808.1.0/x86_64/fedora-coreos-40.20240808.1.0-nutanix.x86_64.qcow2.sig",
                                "sha256": "f6c8be3dbcc8ab4fff87656eac6d30058802e5dcd9ab73380b355678aabb57ed"
                            }
                        }
                    }
                },
                "openstack": {
                    "release": "40.20240808.1.0",
                    "formats": {
                        "qcow2.xz": {
                            "disk": {
                                "location": "https://builds.coreos.fedoraproject.org/prod/streams/next/builds/40.20240808.1.0/x86_64/fedora-coreos-40.20240808.1.0-openstack.x86_64.qcow2.xz",
                                "signature": "https://builds.coreos.fedoraproject.org/prod/streams/next/builds/40.20240808.1.0/x86_64/fedora-coreos-40.20240808.1.0-openstack.x86_64.qcow2.xz.sig",
                                "sha256": "7ef1a1fb3e0fc320ff2bb7791b08d9412ec04e79c5e057d03570bca00569eef9",
                                "uncompressed-sha256": "ec6e58a53e0f27e12cefcf8a55bc4241568621290821b81c6961c6607e1b96c7"
                            }
                        }
                    }
                },
                "qemu": {
                    "release": "40.20240808.1.0",
                    "formats": {
                        "qcow2.xz": {
                            "disk": {
                                "location": "https://builds.coreos.fedoraproject.org/prod/streams/next/builds/40.20240808.1.0/x86_64/fedora-coreos-40.20240808.1.0-qemu.x86_64.qcow2.xz",
                                "signature": "https://builds.coreos.fedoraproject.org/prod/streams/next/builds/40.20240808.1.0/x86_64/fedora-coreos-40.20240808.1.0-qemu.x86_64.qcow2.xz.sig",
                                "sha256": "d201818cb45058d6e54de057ec82d042bc99769eeb6ab13614ebcf9a180a2a10",
                                "uncompressed-sha256": "5cbcb4ff26dd48c92e8a395803391ab91aadf487463560cc611508c69d29f3d0"
                            }
                        }
                    }
                },
                "virtualbox": {
                    "release": "40.20240808.1.0",
                    "formats": {
                        "ova": {
                            "disk": {
                                "location": "https://builds.coreos.fedoraproject.org/prod/streams/next/builds/40.20240808.1.0/x86_64/fedora-coreos-40.20240808.1.0-virtualbox.x86_64.ova",
                                "signature": "https://builds.coreos.fedoraproject.org/prod/streams/next/builds/40.20240808.1.0/x86_64/fedora-coreos-40.20240808.1.0-virtualbox.x86_64.ova.sig",
                                "sha256": "da5073de02a4dfadf2fb23ef88c1fbb2f6a949976d1fba17d8b63d7a15922aef"
                            }
                        }
                    }
                },
                "vmware": {
                    "release": "40.20240808.1.0",
                    "formats": {
                        "ova": {
                            "disk": {
                                "location": "https://builds.coreos.fedoraproject.org/prod/streams/next/builds/40.20240808.1.0/x86_64/fedora-coreos-40.20240808.1.0-vmware.x86_64.ova",
                                "signature": "https://builds.coreos.fedoraproject.org/prod/streams/next/builds/40.20240808.1.0/x86_64/fedora-coreos-40.20240808.1.0-vmware.x86_64.ova.sig",
                                "sha256": "d11bcbb035d2f8e7e888718c3b3ec1cc8f825a39ab602b714ccf6969698cb337"
                            }
                        }
                    }
                },
                "vultr": {
                    "release": "40.20240808.1.0",
                    "formats": {
                        "raw.xz": {
                            "disk": {
                                "location": "https://builds.coreos.fedoraproject.org/prod/streams/next/builds/40.20240808.1.0/x86_64/fedora-coreos-40.20240808.1.0-vultr.x86_64.raw.xz",
                                "signature": "https://builds.coreos.fedoraproject.org/prod/streams/next/builds/40.20240808.1.0/x86_64/fedora-coreos-40.20240808.1.0-vultr.x86_64.raw.xz.sig",
                                "sha256": "430bf3ba5fd7e5cd573102f323d1483f1ba81a37e7c6d4a88b85b03576f9ca63",
                                "uncompressed-sha256": "4bf7e48b44284274ee57bb2980513982662b3bdbac8b2c270172ff066f5e2004"
                            }
                        }
                    }
                }
            },
            "images": {
                "aws": {
                    "regions": {
                        "af-south-1": {
                            "release": "40.20240808.1.0",
                            "image": "ami-0c37351545a26e594"
                        },
                        "ap-east-1": {
                            "release": "40.20240808.1.0",
                            "image": "ami-0332889c59b90caaa"
                        },
                        "ap-northeast-1": {
                            "release": "40.20240808.1.0",
                            "image": "ami-06e9287962afc82a0"
                        },
                        "ap-northeast-2": {
                            "release": "40.20240808.1.0",
                            "image": "ami-0726ed173c506c08a"
                        },
                        "ap-northeast-3": {
                            "release": "40.20240808.1.0",
                            "image": "ami-02c38d4417da699e8"
                        },
                        "ap-south-1": {
                            "release": "40.20240808.1.0",
                            "image": "ami-07e5f83bc2ef7880b"
                        },
                        "ap-south-2": {
                            "release": "40.20240808.1.0",
                            "image": "ami-0febe6d1898204d4b"
                        },
                        "ap-southeast-1": {
                            "release": "40.20240808.1.0",
                            "image": "ami-0af42c45a75efea40"
                        },
                        "ap-southeast-2": {
                            "release": "40.20240808.1.0",
                            "image": "ami-09086704ec19d6504"
                        },
                        "ap-southeast-3": {
                            "release": "40.20240808.1.0",
                            "image": "ami-0c6d895d10f992f66"
                        },
                        "ap-southeast-4": {
                            "release": "40.20240808.1.0",
                            "image": "ami-021f7ce1437df79ef"
                        },
                        "ca-central-1": {
                            "release": "40.20240808.1.0",
                            "image": "ami-0d9418e82af2dae52"
                        },
                        "ca-west-1": {
                            "release": "40.20240808.1.0",
                            "image": "ami-0fbdc3e069f98493b"
                        },
                        "eu-central-1": {
                            "release": "40.20240808.1.0",
                            "image": "ami-04e39fc3020dbf1d0"
                        },
                        "eu-central-2": {
                            "release": "40.20240808.1.0",
                            "image": "ami-00df9bacde3994e71"
                        },
                        "eu-north-1": {
                            "release": "40.20240808.1.0",
                            "image": "ami-02baab6f9ec90f7be"
                        },
                        "eu-south-1": {
                            "release": "40.20240808.1.0",
                            "image": "ami-0c66af539926177fa"
                        },
                        "eu-south-2": {
                            "release": "40.20240808.1.0",
                            "image": "ami-06651947a1ea798de"
                        },
                        "eu-west-1": {
                            "release": "40.20240808.1.0",
                            "image": "ami-00318732602461031"
                        },
                        "eu-west-2": {
                            "release": "40.20240808.1.0",
                            "image": "ami-0c1d66e80ce47c5b4"
                        },
                        "eu-west-3": {
                            "release": "40.20240808.1.0",
                            "image": "ami-043ee58a85e625876"
                        },
                        "il-central-1": {
                            "release": "40.20240808.1.0",
                            "image": "ami-01a2c3de209e4b229"
                        },
                        "me-central-1": {
                            "release": "40.20240808.1.0",
                            "image": "ami-0612aa2614ee64565"
                        },
                        "me-south-1": {
                            "release": "40.20240808.1.0",
                            "image": "ami-08f58076f39bbecf7"
                        },
                        "sa-east-1": {
                            "release": "40.20240808.1.0",
                            "image": "ami-05b73d9b7e0fbc948"
                        },
                        "us-east-1": {
                            "release": "40.20240808.1.0",
                            "image": "ami-06aab3ef1aa8b3c91"
                        },
                        "us-east-2": {
                            "release": "40.20240808.1.0",
                            "image": "ami-0c9b5cd2edc926e6f"
                        },
                        "us-west-1": {
                            "release": "40.20240808.1.0",
                            "image": "ami-09b33548d49bce164"
                        },
                        "us-west-2": {
                            "release": "40.20240808.1.0",
                            "image": "ami-08360e076590d2795"
                        }
                    }
                },
                "gcp": {
                    "release": "40.20240808.1.0",
                    "project": "fedora-coreos-cloud",
                    "family": "fedora-coreos-next",
                    "name": "fedora-coreos-40-20240808-1-0-gcp-x86-64"
                },
                "kubevirt": {
                    "release": "40.20240808.1.0",
                    "image": "quay.io/fedora/fedora-coreos-kubevirt:next",
                    "digest-ref": "quay.io/fedora/fedora-coreos-kubevirt@sha256:c5fc15906df2f41e3c169b2ea0ff6d373292c46e25d597c585cb0cbf6e4990cc"
                }
            }
        }
    }
}
