{
    "stream": "stable",
    "metadata": {
        "last-modified": "2024-01-31T15:59:20Z",
        "generator": "fedora-coreos-stream-generator v0.2.15"
    },
    "architectures": {
        "aarch64": {
            "artifacts": {
                "applehv": {
                    "release": "39.20240112.3.0",
                    "formats": {
                        "raw.gz": {
                            "disk": {
                                "location": "https://builds.coreos.fedoraproject.org/prod/streams/stable/builds/39.20240112.3.0/aarch64/fedora-coreos-39.20240112.3.0-applehv.aarch64.raw.gz",
                                "signature": "https://builds.coreos.fedoraproject.org/prod/streams/stable/builds/39.20240112.3.0/aarch64/fedora-coreos-39.20240112.3.0-applehv.aarch64.raw.gz.sig",
                                "sha256": "aeeb456bfccbf1397b2c1f881ded420bfd0c18dd09cf1cfc1143d78334747fe0",
                                "uncompressed-sha256": "9c4af96f95d8eb7371ccd5d2029f0272710e7bb400915f3f8c81b819e212923e"
                            }
                        }
                    }
                },
                "aws": {
                    "release": "39.20240112.3.0",
                    "formats": {
                        "vmdk.xz": {
                            "disk": {
                                "location": "https://builds.coreos.fedoraproject.org/prod/streams/stable/builds/39.20240112.3.0/aarch64/fedora-coreos-39.20240112.3.0-aws.aarch64.vmdk.xz",
                                "signature": "https://builds.coreos.fedoraproject.org/prod/streams/stable/builds/39.20240112.3.0/aarch64/fedora-coreos-39.20240112.3.0-aws.aarch64.vmdk.xz.sig",
                                "sha256": "aa99e18b37e7fc4eddc5ff4e190c3c35ee443855ce99800502839fd3e244bcbc",
                                "uncompressed-sha256": "fad4de14c2e3422165dfe3a90bf8cd5447c22681479312db9cd2a50e12a8b996"
                            }
                        }
                    }
                },
                "azure": {
                    "release": "39.20240112.3.0",
                    "formats": {
                        "vhd.xz": {
                            "disk": {
                                "location": "https://builds.coreos.fedoraproject.org/prod/streams/stable/builds/39.20240112.3.0/aarch64/fedora-coreos-39.20240112.3.0-azure.aarch64.vhd.xz",
                                "signature": "https://builds.coreos.fedoraproject.org/prod/streams/stable/builds/39.20240112.3.0/aarch64/fedora-coreos-39.20240112.3.0-azure.aarch64.vhd.xz.sig",
                                "sha256": "ce80440bfd5dde6e3de28690fcf9a4941b8da06008b2bbf07a4e16bf7f286ea0",
                                "uncompressed-sha256": "3157af69af86bcd55950b3f0daa55f84d2f68f3da0de134482bb3dded05dad56"
                            }
                        }
                    }
                },
                "gcp": {
                    "release": "39.20240112.3.0",
                    "formats": {
                        "tar.gz": {
                            "disk": {
                                "location": "https://builds.coreos.fedoraproject.org/prod/streams/stable/builds/39.20240112.3.0/aarch64/fedora-coreos-39.20240112.3.0-gcp.aarch64.tar.gz",
                                "signature": "https://builds.coreos.fedoraproject.org/prod/streams/stable/builds/39.20240112.3.0/aarch64/fedora-coreos-39.20240112.3.0-gcp.aarch64.tar.gz.sig",
                                "sha256": "9d85ee986179fc9dfb0ecfed8e378edd254cf37e49c1a90112fe91b8170883d3",
                                "uncompressed-sha256": "5f8e9c1ccead3d5b422ba1ad4c7a2c8e98c414a44fb008807e841f3c7311033a"
                            }
                        }
                    }
                },
                "hyperv": {
                    "release": "39.20240112.3.0",
                    "formats": {
                        "vhdx.zip": {
                            "disk": {
                                "location": "https://builds.coreos.fedoraproject.org/prod/streams/stable/builds/39.20240112.3.0/aarch64/fedora-coreos-39.20240112.3.0-hyperv.aarch64.vhdx.zip",
                                "signature": "https://builds.coreos.fedoraproject.org/prod/streams/stable/builds/39.20240112.3.0/aarch64/fedora-coreos-39.20240112.3.0-hyperv.aarch64.vhdx.zip.sig",
                                "sha256": "c609169da9d4d2a090d178591c9d33eff024b338211fba4579b1575d8a6728f4",
                                "uncompressed-sha256": "54a1423c276f6ceeccd3f6cd7ba1fb020dc05a9531f5a40cc768acadf5ff73b0"
                            }
                        }
                    }
                },
                "metal": {
                    "release": "39.20240112.3.0",
                    "formats": {
                        "4k.raw.xz": {
                            "disk": {
                                "location": "https://builds.coreos.fedoraproject.org/prod/streams/stable/builds/39.20240112.3.0/aarch64/fedora-coreos-39.20240112.3.0-metal4k.aarch64.raw.xz",
                                "signature": "https://builds.coreos.fedoraproject.org/prod/streams/stable/builds/39.20240112.3.0/aarch64/fedora-coreos-39.20240112.3.0-metal4k.aarch64.raw.xz.sig",
                                "sha256": "116678f8b2c954426cca44afe0311920fcf159c3003aea25af2c750de841172e",
                                "uncompressed-sha256": "4caa2f3c0818bac90d411ee870d0726f70336314e182375ba753ff4dd994c248"
                            }
                        },
                        "iso": {
                            "disk": {
                                "location": "https://builds.coreos.fedoraproject.org/prod/streams/stable/builds/39.20240112.3.0/aarch64/fedora-coreos-39.20240112.3.0-live.aarch64.iso",
                                "signature": "https://builds.coreos.fedoraproject.org/prod/streams/stable/builds/39.20240112.3.0/aarch64/fedora-coreos-39.20240112.3.0-live.aarch64.iso.sig",
                                "sha256": "681c46279f821f51a2af21a677610487dae56559554fc83a13b98f7bf1d696ab"
                            }
                        },
                        "pxe": {
                            "kernel": {
                                "location": "https://builds.coreos.fedoraproject.org/prod/streams/stable/builds/39.20240112.3.0/aarch64/fedora-coreos-39.20240112.3.0-live-kernel-aarch64",
                                "signature": "https://builds.coreos.fedoraproject.org/prod/streams/stable/builds/39.20240112.3.0/aarch64/fedora-coreos-39.20240112.3.0-live-kernel-aarch64.sig",
                                "sha256": "608bca9610637faad7d468c5e03019ef81a903cd0a3ddc83cc4f693729b661d0"
                            },
                            "initramfs": {
                                "location": "https://builds.coreos.fedoraproject.org/prod/streams/stable/builds/39.20240112.3.0/aarch64/fedora-coreos-39.20240112.3.0-live-initramfs.aarch64.img",
                                "signature": "https://builds.coreos.fedoraproject.org/prod/streams/stable/builds/39.20240112.3.0/aarch64/fedora-coreos-39.20240112.3.0-live-initramfs.aarch64.img.sig",
                                "sha256": "4a6a36d08414cd5fec0e915fa15b9815921041d0ab85a9f6b92093e629cb419c"
                            },
                            "rootfs": {
                                "location": "https://builds.coreos.fedoraproject.org/prod/streams/stable/builds/39.20240112.3.0/aarch64/fedora-coreos-39.20240112.3.0-live-rootfs.aarch64.img",
                                "signature": "https://builds.coreos.fedoraproject.org/prod/streams/stable/builds/39.20240112.3.0/aarch64/fedora-coreos-39.20240112.3.0-live-rootfs.aarch64.img.sig",
                                "sha256": "174f877651b660a8181333d4cc55fcaf9d96ac65957dc125923eec466feed742"
                            }
                        },
                        "raw.xz": {
                            "disk": {
                                "location": "https://builds.coreos.fedoraproject.org/prod/streams/stable/builds/39.20240112.3.0/aarch64/fedora-coreos-39.20240112.3.0-metal.aarch64.raw.xz",
                                "signature": "https://builds.coreos.fedoraproject.org/prod/streams/stable/builds/39.20240112.3.0/aarch64/fedora-coreos-39.20240112.3.0-metal.aarch64.raw.xz.sig",
                                "sha256": "6ecb90b0528c5de45c2656554aed6ea6e914ed415f5ed9a07576583df7732281",
                                "uncompressed-sha256": "5e2cfa7d1a04c1158d0ead832b9af2dab7a1c67ad686d9139878ab5ebce6e281"
                            }
                        }
                    }
                },
                "openstack": {
                    "release": "39.20240112.3.0",
                    "formats": {
                        "qcow2.xz": {
                            "disk": {
                                "location": "https://builds.coreos.fedoraproject.org/prod/streams/stable/builds/39.20240112.3.0/aarch64/fedora-coreos-39.20240112.3.0-openstack.aarch64.qcow2.xz",
                                "signature": "https://builds.coreos.fedoraproject.org/prod/streams/stable/builds/39.20240112.3.0/aarch64/fedora-coreos-39.20240112.3.0-openstack.aarch64.qcow2.xz.sig",
                                "sha256": "37f6ad55d207f2e89ff3e8cf4caecfa0661c15dbc8a96ebb0ab035751e32fb2e",
                                "uncompressed-sha256": "39c7f9fc8254bc7a04b564de5230ade532bdb2ecf75e8e2f25fb61885280f419"
                            }
                        }
                    }
                },
                "qemu": {
                    "release": "39.20240112.3.0",
                    "formats": {
                        "qcow2.xz": {
                            "disk": {
                                "location": "https://builds.coreos.fedoraproject.org/prod/streams/stable/builds/39.20240112.3.0/aarch64/fedora-coreos-39.20240112.3.0-qemu.aarch64.qcow2.xz",
                                "signature": "https://builds.coreos.fedoraproject.org/prod/streams/stable/builds/39.20240112.3.0/aarch64/fedora-coreos-39.20240112.3.0-qemu.aarch64.qcow2.xz.sig",
                                "sha256": "ea9496dba2a3ef031d7fa2c2f970a6f26fdac0c42983f169576d4c8a85726daf",
                                "uncompressed-sha256": "ffc154e06e096f21fe92c6461edb14518216be0220c12b9784293c724e85c3a5"
                            }
                        }
                    }
                }
            },
            "images": {
                "aws": {
                    "regions": {
                        "af-south-1": {
                            "release": "39.20240112.3.0",
                            "image": "ami-053cf73c554d11f6d"
                        },
                        "ap-east-1": {
                            "release": "39.20240112.3.0",
                            "image": "ami-0ac08fbae1f1247db"
                        },
                        "ap-northeast-1": {
                            "release": "39.20240112.3.0",
                            "image": "ami-082e61379d30e1b7f"
                        },
                        "ap-northeast-2": {
                            "release": "39.20240112.3.0",
                            "image": "ami-0697587a1d890fbda"
                        },
                        "ap-northeast-3": {
                            "release": "39.20240112.3.0",
                            "image": "ami-0c8d43ed62104b847"
                        },
                        "ap-south-1": {
                            "release": "39.20240112.3.0",
                            "image": "ami-0f6cbc57b9f01bec6"
                        },
                        "ap-south-2": {
                            "release": "39.20240112.3.0",
                            "image": "ami-03f4794cdd9d81384"
                        },
                        "ap-southeast-1": {
                            "release": "39.20240112.3.0",
                            "image": "ami-090af9adceb1b1cbd"
                        },
                        "ap-southeast-2": {
                            "release": "39.20240112.3.0",
                            "image": "ami-0a6ecd045cc51bbef"
                        },
                        "ap-southeast-3": {
                            "release": "39.20240112.3.0",
                            "image": "ami-0d5c9cb4eed2924be"
                        },
                        "ap-southeast-4": {
                            "release": "39.20240112.3.0",
                            "image": "ami-0978cef15ad866583"
                        },
                        "ca-central-1": {
                            "release": "39.20240112.3.0",
                            "image": "ami-081fb4f58dffbefc3"
                        },
                        "ca-west-1": {
                            "release": "39.20240112.3.0",
                            "image": "ami-05fca6303f5d096a8"
                        },
                        "eu-central-1": {
                            "release": "39.20240112.3.0",
                            "image": "ami-078952ad811595167"
                        },
                        "eu-central-2": {
                            "release": "39.20240112.3.0",
                            "image": "ami-0b93991c13d37ffc5"
                        },
                        "eu-north-1": {
                            "release": "39.20240112.3.0",
                            "image": "ami-0298d6205ed226ef8"
                        },
                        "eu-south-1": {
                            "release": "39.20240112.3.0",
                            "image": "ami-00b2a25297a6af7da"
                        },
                        "eu-south-2": {
                            "release": "39.20240112.3.0",
                            "image": "ami-0a4d6287aa1af7da5"
                        },
                        "eu-west-1": {
                            "release": "39.20240112.3.0",
                            "image": "ami-04b4bd5e032719ba6"
                        },
                        "eu-west-2": {
                            "release": "39.20240112.3.0",
                            "image": "ami-025b273cd18e6dd91"
                        },
                        "eu-west-3": {
                            "release": "39.20240112.3.0",
                            "image": "ami-02f5f6f098ae6ef25"
                        },
                        "il-central-1": {
                            "release": "39.20240112.3.0",
                            "image": "ami-070f3d2f5bb3ba0a2"
                        },
                        "me-central-1": {
                            "release": "39.20240112.3.0",
                            "image": "ami-041b243efbc255f7f"
                        },
                        "me-south-1": {
                            "release": "39.20240112.3.0",
                            "image": "ami-084483dbe064d81a8"
                        },
                        "sa-east-1": {
                            "release": "39.20240112.3.0",
                            "image": "ami-0d043a12103d4ae76"
                        },
                        "us-east-1": {
                            "release": "39.20240112.3.0",
                            "image": "ami-0bf84607b1a7e2218"
                        },
                        "us-east-2": {
                            "release": "39.20240112.3.0",
                            "image": "ami-0c8c03c6d6da33170"
                        },
                        "us-west-1": {
                            "release": "39.20240112.3.0",
                            "image": "ami-051479cd56e25ba8c"
                        },
                        "us-west-2": {
                            "release": "39.20240112.3.0",
                            "image": "ami-0f1fbf51815534c9d"
                        }
                    }
                },
                "gcp": {
                    "release": "39.20240112.3.0",
                    "project": "fedora-coreos-cloud",
                    "family": "fedora-coreos-stable-arm64",
                    "name": "fedora-coreos-39-20240112-3-0-gcp-aarch64"
                }
            }
        },
        "ppc64le": {
            "artifacts": {
                "metal": {
                    "release": "39.20240112.3.0",
                    "formats": {
                        "4k.raw.xz": {
                            "disk": {
                                "location": "https://builds.coreos.fedoraproject.org/prod/streams/stable/builds/39.20240112.3.0/ppc64le/fedora-coreos-39.20240112.3.0-metal4k.ppc64le.raw.xz",
                                "signature": "https://builds.coreos.fedoraproject.org/prod/streams/stable/builds/39.20240112.3.0/ppc64le/fedora-coreos-39.20240112.3.0-metal4k.ppc64le.raw.xz.sig",
                                "sha256": "9d24c611689423f7ed2120e72a167ddec949356d8cec2f15d80821ae240f4c69",
                                "uncompressed-sha256": "1ce6178dedee1eb81e901ec57cf22730fb5f3cd9b7f35488654fcef95a2baca7"
                            }
                        },
                        "iso": {
                            "disk": {
                                "location": "https://builds.coreos.fedoraproject.org/prod/streams/stable/builds/39.20240112.3.0/ppc64le/fedora-coreos-39.20240112.3.0-live.ppc64le.iso",
                                "signature": "https://builds.coreos.fedoraproject.org/prod/streams/stable/builds/39.20240112.3.0/ppc64le/fedora-coreos-39.20240112.3.0-live.ppc64le.iso.sig",
                                "sha256": "d87f321947a6bb76838737f51326deeca58fe9753872e91e3b4cd7b79530fa5c"
                            }
                        },
                        "pxe": {
                            "kernel": {
                                "location": "https://builds.coreos.fedoraproject.org/prod/streams/stable/builds/39.20240112.3.0/ppc64le/fedora-coreos-39.20240112.3.0-live-kernel-ppc64le",
                                "signature": "https://builds.coreos.fedoraproject.org/prod/streams/stable/builds/39.20240112.3.0/ppc64le/fedora-coreos-39.20240112.3.0-live-kernel-ppc64le.sig",
                                "sha256": "1ac57384bf7457f3a130dd6672a771e1e1df503f68ed16f1f70cfb05ea911aa7"
                            },
                            "initramfs": {
                                "location": "https://builds.coreos.fedoraproject.org/prod/streams/stable/builds/39.20240112.3.0/ppc64le/fedora-coreos-39.20240112.3.0-live-initramfs.ppc64le.img",
                                "signature": "https://builds.coreos.fedoraproject.org/prod/streams/stable/builds/39.20240112.3.0/ppc64le/fedora-coreos-39.20240112.3.0-live-initramfs.ppc64le.img.sig",
                                "sha256": "d8657b8eea71acfe97c90672f27a66e2e1d8d4dffce8e5105ef6ce2fe702f381"
                            },
                            "rootfs": {
                                "location": "https://builds.coreos.fedoraproject.org/prod/streams/stable/builds/39.20240112.3.0/ppc64le/fedora-coreos-39.20240112.3.0-live-rootfs.ppc64le.img",
                                "signature": "https://builds.coreos.fedoraproject.org/prod/streams/stable/builds/39.20240112.3.0/ppc64le/fedora-coreos-39.20240112.3.0-live-rootfs.ppc64le.img.sig",
                                "sha256": "23d61a62d6223a41b1782b768aaad1d254a51d6dd6387c9ce17e542b1390e051"
                            }
                        },
                        "raw.xz": {
                            "disk": {
                                "location": "https://builds.coreos.fedoraproject.org/prod/streams/stable/builds/39.20240112.3.0/ppc64le/fedora-coreos-39.20240112.3.0-metal.ppc64le.raw.xz",
                                "signature": "https://builds.coreos.fedoraproject.org/prod/streams/stable/builds/39.20240112.3.0/ppc64le/fedora-coreos-39.20240112.3.0-metal.ppc64le.raw.xz.sig",
                                "sha256": "a7d7ed17fc01539f05e8b71f2b3a942cd40f3d6acd349f1a4e488f5bcbda058f",
                                "uncompressed-sha256": "ed0ca6530eb1f7fec3a2dc50464d313073621b59716843979d086747c132bab0"
                            }
                        }
                    }
                },
                "openstack": {
                    "release": "39.20240112.3.0",
                    "formats": {
                        "qcow2.xz": {
                            "disk": {
                                "location": "https://builds.coreos.fedoraproject.org/prod/streams/stable/builds/39.20240112.3.0/ppc64le/fedora-coreos-39.20240112.3.0-openstack.ppc64le.qcow2.xz",
                                "signature": "https://builds.coreos.fedoraproject.org/prod/streams/stable/builds/39.20240112.3.0/ppc64le/fedora-coreos-39.20240112.3.0-openstack.ppc64le.qcow2.xz.sig",
                                "sha256": "69194a1a261fae28f69fecf1b41808e72fcfdbcd10fe5b578c399455a077e49f",
                                "uncompressed-sha256": "8d3a2224ef2e4cdbc1af002e22e1cc584449616eb52236626bc5b0a55e079160"
                            }
                        }
                    }
                },
                "powervs": {
                    "release": "39.20240112.3.0",
                    "formats": {
                        "ova.gz": {
                            "disk": {
                                "location": "https://builds.coreos.fedoraproject.org/prod/streams/stable/builds/39.20240112.3.0/ppc64le/fedora-coreos-39.20240112.3.0-powervs.ppc64le.ova.gz",
                                "signature": "https://builds.coreos.fedoraproject.org/prod/streams/stable/builds/39.20240112.3.0/ppc64le/fedora-coreos-39.20240112.3.0-powervs.ppc64le.ova.gz.sig",
                                "sha256": "3352f5a5efba03b91bc0a2bf45fdba8ca058c3db93583a8c00cc184123fd9689",
                                "uncompressed-sha256": "f96213b03967c9f859ff119a676665007cc818507a2609f616277c9dc8a58a19"
                            }
                        }
                    }
                },
                "qemu": {
                    "release": "39.20240112.3.0",
                    "formats": {
                        "qcow2.xz": {
                            "disk": {
                                "location": "https://builds.coreos.fedoraproject.org/prod/streams/stable/builds/39.20240112.3.0/ppc64le/fedora-coreos-39.20240112.3.0-qemu.ppc64le.qcow2.xz",
                                "signature": "https://builds.coreos.fedoraproject.org/prod/streams/stable/builds/39.20240112.3.0/ppc64le/fedora-coreos-39.20240112.3.0-qemu.ppc64le.qcow2.xz.sig",
                                "sha256": "b95ed6c24d7a9100e03096ebe15c2452d24227830b67c6ba3e8107714b8a91fe",
                                "uncompressed-sha256": "00eeb27ab7f683c7387958001f85d476b2f771599f67c26b94c50660a637664c"
                            }
                        }
                    }
                }
            },
            "images": {}
        },
        "s390x": {
            "artifacts": {
                "ibmcloud": {
                    "release": "39.20240112.3.0",
                    "formats": {
                        "qcow2.xz": {
                            "disk": {
                                "location": "https://builds.coreos.fedoraproject.org/prod/streams/stable/builds/39.20240112.3.0/s390x/fedora-coreos-39.20240112.3.0-ibmcloud.s390x.qcow2.xz",
                                "signature": "https://builds.coreos.fedoraproject.org/prod/streams/stable/builds/39.20240112.3.0/s390x/fedora-coreos-39.20240112.3.0-ibmcloud.s390x.qcow2.xz.sig",
                                "sha256": "21efbadf531588117535c11c81acd52beb8fa4ac1ebd95e88644a7bf653af763",
                                "uncompressed-sha256": "9ab4ff4994e94ce2edfe1b4ffb5c35314f1742f4baf45c164334e06792f47b60"
                            }
                        }
                    }
                },
                "metal": {
                    "release": "39.20240112.3.0",
                    "formats": {
                        "4k.raw.xz": {
                            "disk": {
                                "location": "https://builds.coreos.fedoraproject.org/prod/streams/stable/builds/39.20240112.3.0/s390x/fedora-coreos-39.20240112.3.0-metal4k.s390x.raw.xz",
                                "signature": "https://builds.coreos.fedoraproject.org/prod/streams/stable/builds/39.20240112.3.0/s390x/fedora-coreos-39.20240112.3.0-metal4k.s390x.raw.xz.sig",
                                "sha256": "9795345259e89b64e3a91c053bccd17e1127e1afcb2eb6d346241db69f60cd3b",
                                "uncompressed-sha256": "c91a2f18714b82b81befec6446b1f2ec97ce71abbeaf0c844b7181fb9399c13a"
                            }
                        },
                        "iso": {
                            "disk": {
                                "location": "https://builds.coreos.fedoraproject.org/prod/streams/stable/builds/39.20240112.3.0/s390x/fedora-coreos-39.20240112.3.0-live.s390x.iso",
                                "signature": "https://builds.coreos.fedoraproject.org/prod/streams/stable/builds/39.20240112.3.0/s390x/fedora-coreos-39.20240112.3.0-live.s390x.iso.sig",
                                "sha256": "97d5959734243428bdbbbd20a40f786337cc89e214d8ea3c842d9b4e8fec9510"
                            }
                        },
                        "pxe": {
                            "kernel": {
                                "location": "https://builds.coreos.fedoraproject.org/prod/streams/stable/builds/39.20240112.3.0/s390x/fedora-coreos-39.20240112.3.0-live-kernel-s390x",
                                "signature": "https://builds.coreos.fedoraproject.org/prod/streams/stable/builds/39.20240112.3.0/s390x/fedora-coreos-39.20240112.3.0-live-kernel-s390x.sig",
                                "sha256": "08c1bdfe60e2fcde9b226db19736e6a468aa128c8b39516e8548512209b1ffa1"
                            },
                            "initramfs": {
                                "location": "https://builds.coreos.fedoraproject.org/prod/streams/stable/builds/39.20240112.3.0/s390x/fedora-coreos-39.20240112.3.0-live-initramfs.s390x.img",
                                "signature": "https://builds.coreos.fedoraproject.org/prod/streams/stable/builds/39.20240112.3.0/s390x/fedora-coreos-39.20240112.3.0-live-initramfs.s390x.img.sig",
                                "sha256": "bf6a6dc3e7a9b11f1b1efab5a26cf73fa287d7035d7da5faa1760c49d6a502b7"
                            },
                            "rootfs": {
                                "location": "https://builds.coreos.fedoraproject.org/prod/streams/stable/builds/39.20240112.3.0/s390x/fedora-coreos-39.20240112.3.0-live-rootfs.s390x.img",
                                "signature": "https://builds.coreos.fedoraproject.org/prod/streams/stable/builds/39.20240112.3.0/s390x/fedora-coreos-39.20240112.3.0-live-rootfs.s390x.img.sig",
                                "sha256": "b1068ee07171dc6d8f2682ab4cf8eabe980e39122bf1558a63a3ed48b152c7f3"
                            }
                        },
                        "raw.xz": {
                            "disk": {
                                "location": "https://builds.coreos.fedoraproject.org/prod/streams/stable/builds/39.20240112.3.0/s390x/fedora-coreos-39.20240112.3.0-metal.s390x.raw.xz",
                                "signature": "https://builds.coreos.fedoraproject.org/prod/streams/stable/builds/39.20240112.3.0/s390x/fedora-coreos-39.20240112.3.0-metal.s390x.raw.xz.sig",
                                "sha256": "2b5f3aa87a1c7f401e525ed99b57cb82061296d5ed8dd9e49a7d83b3dd15675a",
                                "uncompressed-sha256": "ff6e32b30a763684e6624adb013fd71fe05ed7dae921a033f99a2027814fced7"
                            }
                        }
                    }
                },
                "openstack": {
                    "release": "39.20240112.3.0",
                    "formats": {
                        "qcow2.xz": {
                            "disk": {
                                "location": "https://builds.coreos.fedoraproject.org/prod/streams/stable/builds/39.20240112.3.0/s390x/fedora-coreos-39.20240112.3.0-openstack.s390x.qcow2.xz",
                                "signature": "https://builds.coreos.fedoraproject.org/prod/streams/stable/builds/39.20240112.3.0/s390x/fedora-coreos-39.20240112.3.0-openstack.s390x.qcow2.xz.sig",
                                "sha256": "dc3706d2828d9e6d11ce7b74ca7626fa3ee494acbf87b375eae742adb26961f4",
                                "uncompressed-sha256": "ba7c8e2da6a739ae3ba7050cf1cebf590c4710bf354cc5a58559e5e231f90842"
                            }
                        }
                    }
                },
                "qemu": {
                    "release": "39.20240112.3.0",
                    "formats": {
                        "qcow2.xz": {
                            "disk": {
                                "location": "https://builds.coreos.fedoraproject.org/prod/streams/stable/builds/39.20240112.3.0/s390x/fedora-coreos-39.20240112.3.0-qemu.s390x.qcow2.xz",
                                "signature": "https://builds.coreos.fedoraproject.org/prod/streams/stable/builds/39.20240112.3.0/s390x/fedora-coreos-39.20240112.3.0-qemu.s390x.qcow2.xz.sig",
                                "sha256": "7826deb756bf6f290ad1c394261efb6ec5920d46ca27533721294f343454b4aa",
                                "uncompressed-sha256": "a605bcec75d47de533bb5fc88b26a8071010e9235e1c9ccbc1200f3ee48d4c26"
                            }
                        }
                    }
                }
            },
            "images": {}
        },
        "x86_64": {
            "artifacts": {
                "aliyun": {
                    "release": "39.20240112.3.0",
                    "formats": {
                        "qcow2.xz": {
                            "disk": {
                                "location": "https://builds.coreos.fedoraproject.org/prod/streams/stable/builds/39.20240112.3.0/x86_64/fedora-coreos-39.20240112.3.0-aliyun.x86_64.qcow2.xz",
                                "signature": "https://builds.coreos.fedoraproject.org/prod/streams/stable/builds/39.20240112.3.0/x86_64/fedora-coreos-39.20240112.3.0-aliyun.x86_64.qcow2.xz.sig",
                                "sha256": "44664a4c888704217c3299eb0897957ceb2503a9473b3bca89ea184a505217aa",
                                "uncompressed-sha256": "90c41e29acfbb0ff15fd4211da31dff133d6cb8fdb7697c2c24f5d0ae0a94802"
                            }
                        }
                    }
                },
                "applehv": {
                    "release": "39.20240112.3.0",
                    "formats": {
                        "raw.gz": {
                            "disk": {
                                "location": "https://builds.coreos.fedoraproject.org/prod/streams/stable/builds/39.20240112.3.0/x86_64/fedora-coreos-39.20240112.3.0-applehv.x86_64.raw.gz",
                                "signature": "https://builds.coreos.fedoraproject.org/prod/streams/stable/builds/39.20240112.3.0/x86_64/fedora-coreos-39.20240112.3.0-applehv.x86_64.raw.gz.sig",
                                "sha256": "ec036b7076bfd5df7e4912a21312c2fe0c266775c1f6f48876facc848291475d",
                                "uncompressed-sha256": "71223679452acaeaa6e62b9cdd824d620a34aed15afa539e52125be2223ef3d0"
                            }
                        }
                    }
                },
                "aws": {
                    "release": "39.20240112.3.0",
                    "formats": {
                        "vmdk.xz": {
                            "disk": {
                                "location": "https://builds.coreos.fedoraproject.org/prod/streams/stable/builds/39.20240112.3.0/x86_64/fedora-coreos-39.20240112.3.0-aws.x86_64.vmdk.xz",
                                "signature": "https://builds.coreos.fedoraproject.org/prod/streams/stable/builds/39.20240112.3.0/x86_64/fedora-coreos-39.20240112.3.0-aws.x86_64.vmdk.xz.sig",
                                "sha256": "b307e61d48ce1773ffc9d31a58fe5e867df5d613f3ffd161eb994c21b1cc35a5",
                                "uncompressed-sha256": "ddaea6a5fc74fb5a31897fa8dc23e9ae1c805be0052560e1fdaada5b3a940dfc"
                            }
                        }
                    }
                },
                "azure": {
                    "release": "39.20240112.3.0",
                    "formats": {
                        "vhd.xz": {
                            "disk": {
                                "location": "https://builds.coreos.fedoraproject.org/prod/streams/stable/builds/39.20240112.3.0/x86_64/fedora-coreos-39.20240112.3.0-azure.x86_64.vhd.xz",
                                "signature": "https://builds.coreos.fedoraproject.org/prod/streams/stable/builds/39.20240112.3.0/x86_64/fedora-coreos-39.20240112.3.0-azure.x86_64.vhd.xz.sig",
                                "sha256": "2b0037e5dff3c790be93504cf925fb0dc3d731d02600bc606d1d28584f926a7a",
                                "uncompressed-sha256": "76c73237865124036b3bc197333aa18c424df9e2163479bf6b1f1aee908d3b42"
                            }
                        }
                    }
                },
                "azurestack": {
                    "release": "39.20240112.3.0",
                    "formats": {
                        "vhd.xz": {
                            "disk": {
                                "location": "https://builds.coreos.fedoraproject.org/prod/streams/stable/builds/39.20240112.3.0/x86_64/fedora-coreos-39.20240112.3.0-azurestack.x86_64.vhd.xz",
                                "signature": "https://builds.coreos.fedoraproject.org/prod/streams/stable/builds/39.20240112.3.0/x86_64/fedora-coreos-39.20240112.3.0-azurestack.x86_64.vhd.xz.sig",
                                "sha256": "09c26ccf17fa40880b37c757783bf1c133b8a94273090c70e58469f6eaa4e2b4",
                                "uncompressed-sha256": "243b8a2b3e4423449c116b1341ae35da46a387da7063b4fcfe485be3edd8f3db"
                            }
                        }
                    }
                },
                "digitalocean": {
                    "release": "39.20240112.3.0",
                    "formats": {
                        "qcow2.gz": {
                            "disk": {
                                "location": "https://builds.coreos.fedoraproject.org/prod/streams/stable/builds/39.20240112.3.0/x86_64/fedora-coreos-39.20240112.3.0-digitalocean.x86_64.qcow2.gz",
                                "signature": "https://builds.coreos.fedoraproject.org/prod/streams/stable/builds/39.20240112.3.0/x86_64/fedora-coreos-39.20240112.3.0-digitalocean.x86_64.qcow2.gz.sig",
                                "sha256": "660eb32a56805363c90428caf309baf540e8268b0f06886c7b5f9104ee19177e",
                                "uncompressed-sha256": "138b0af93a51f9db4617eb8d07b7a04392fa42da03add80bd1e4e84f26ea9a87"
                            }
                        }
                    }
                },
                "exoscale": {
                    "release": "39.20240112.3.0",
                    "formats": {
                        "qcow2.xz": {
                            "disk": {
                                "location": "https://builds.coreos.fedoraproject.org/prod/streams/stable/builds/39.20240112.3.0/x86_64/fedora-coreos-39.20240112.3.0-exoscale.x86_64.qcow2.xz",
                                "signature": "https://builds.coreos.fedoraproject.org/prod/streams/stable/builds/39.20240112.3.0/x86_64/fedora-coreos-39.20240112.3.0-exoscale.x86_64.qcow2.xz.sig",
                                "sha256": "3541fdddcb5d391a0195da0c772c99dc75a6b06bb55e1e8da2aadad05a406838",
                                "uncompressed-sha256": "a1046d2da49350e2927a1baf3f6af9110851b3ea50f70b0631001fc093686c90"
                            }
                        }
                    }
                },
                "gcp": {
                    "release": "39.20240112.3.0",
                    "formats": {
                        "tar.gz": {
                            "disk": {
                                "location": "https://builds.coreos.fedoraproject.org/prod/streams/stable/builds/39.20240112.3.0/x86_64/fedora-coreos-39.20240112.3.0-gcp.x86_64.tar.gz",
                                "signature": "https://builds.coreos.fedoraproject.org/prod/streams/stable/builds/39.20240112.3.0/x86_64/fedora-coreos-39.20240112.3.0-gcp.x86_64.tar.gz.sig",
                                "sha256": "0220cf007696df6719760a0404cce10d0db02b4abc21d9c191bbde38f1de7b8e",
                                "uncompressed-sha256": "bba84bed4c4e5e572ed5e52996878a3349fb25a4e964b510cdcb4d462e216c1e"
                            }
                        }
                    }
                },
                "hyperv": {
                    "release": "39.20240112.3.0",
                    "formats": {
                        "vhdx.zip": {
                            "disk": {
                                "location": "https://builds.coreos.fedoraproject.org/prod/streams/stable/builds/39.20240112.3.0/x86_64/fedora-coreos-39.20240112.3.0-hyperv.x86_64.vhdx.zip",
                                "signature": "https://builds.coreos.fedoraproject.org/prod/streams/stable/builds/39.20240112.3.0/x86_64/fedora-coreos-39.20240112.3.0-hyperv.x86_64.vhdx.zip.sig",
                                "sha256": "19e9f7929ee50f0851f165865d8965fa4155eab91242fed561f50f7d8e2d37f9",
                                "uncompressed-sha256": "f48f56f6f3a61e0493d41b19e5d14761d0092b07c30b1df2f19a2c73bf2b0db6"
                            }
                        }
                    }
                },
                "ibmcloud": {
                    "release": "39.20240112.3.0",
                    "formats": {
                        "qcow2.xz": {
                            "disk": {
                                "location": "https://builds.coreos.fedoraproject.org/prod/streams/stable/builds/39.20240112.3.0/x86_64/fedora-coreos-39.20240112.3.0-ibmcloud.x86_64.qcow2.xz",
                                "signature": "https://builds.coreos.fedoraproject.org/prod/streams/stable/builds/39.20240112.3.0/x86_64/fedora-coreos-39.20240112.3.0-ibmcloud.x86_64.qcow2.xz.sig",
                                "sha256": "4b4286cabd90560f90656b4cd8434626b335914289091137dd549c6a5f377428",
                                "uncompressed-sha256": "c76102135a4910d5072296aa1fbbacae300851618cc3c6ed7aed201e8d261105"
                            }
                        }
                    }
                },
                "kubevirt": {
                    "release": "39.20240112.3.0",
                    "formats": {
                        "ociarchive": {
                            "disk": {
                                "location": "https://builds.coreos.fedoraproject.org/prod/streams/stable/builds/39.20240112.3.0/x86_64/fedora-coreos-39.20240112.3.0-kubevirt.x86_64.ociarchive",
                                "signature": "https://builds.coreos.fedoraproject.org/prod/streams/stable/builds/39.20240112.3.0/x86_64/fedora-coreos-39.20240112.3.0-kubevirt.x86_64.ociarchive.sig",
                                "sha256": "9053b61b84c472ceee5af8de18de89ca6351ee2d723542ea6057d2ab8023e36a"
                            }
                        }
                    }
                },
                "metal": {
                    "release": "39.20240112.3.0",
                    "formats": {
                        "4k.raw.xz": {
                            "disk": {
                                "location": "https://builds.coreos.fedoraproject.org/prod/streams/stable/builds/39.20240112.3.0/x86_64/fedora-coreos-39.20240112.3.0-metal4k.x86_64.raw.xz",
                                "signature": "https://builds.coreos.fedoraproject.org/prod/streams/stable/builds/39.20240112.3.0/x86_64/fedora-coreos-39.20240112.3.0-metal4k.x86_64.raw.xz.sig",
                                "sha256": "c96da2aa328c6e3da261e98a2c4526c3b1aff4fcbdee82427cf774ca0a124573",
                                "uncompressed-sha256": "fa82775555a852e75fa33d7eee8c3b9b0de039a6627d4c17918a6b61cb8f55ae"
                            }
                        },
                        "iso": {
                            "disk": {
                                "location": "https://builds.coreos.fedoraproject.org/prod/streams/stable/builds/39.20240112.3.0/x86_64/fedora-coreos-39.20240112.3.0-live.x86_64.iso",
                                "signature": "https://builds.coreos.fedoraproject.org/prod/streams/stable/builds/39.20240112.3.0/x86_64/fedora-coreos-39.20240112.3.0-live.x86_64.iso.sig",
                                "sha256": "d34520e35c75edf85df47a9d77e42f095253ec78e2dfc4ebdc497a5c790eda2d"
                            }
                        },
                        "pxe": {
                            "kernel": {
                                "location": "https://builds.coreos.fedoraproject.org/prod/streams/stable/builds/39.20240112.3.0/x86_64/fedora-coreos-39.20240112.3.0-live-kernel-x86_64",
                                "signature": "https://builds.coreos.fedoraproject.org/prod/streams/stable/builds/39.20240112.3.0/x86_64/fedora-coreos-39.20240112.3.0-live-kernel-x86_64.sig",
                                "sha256": "ee39b5da6bf3bce33a573a2e5ceec012955d90378b11260472b0030f689d07bf"
                            },
                            "initramfs": {
                                "location": "https://builds.coreos.fedoraproject.org/prod/streams/stable/builds/39.20240112.3.0/x86_64/fedora-coreos-39.20240112.3.0-live-initramfs.x86_64.img",
                                "signature": "https://builds.coreos.fedoraproject.org/prod/streams/stable/builds/39.20240112.3.0/x86_64/fedora-coreos-39.20240112.3.0-live-initramfs.x86_64.img.sig",
                                "sha256": "97edba3e5e7214bedfae920d95243e5f178b10d229d530135a694920a1788deb"
                            },
                            "rootfs": {
                                "location": "https://builds.coreos.fedoraproject.org/prod/streams/stable/builds/39.20240112.3.0/x86_64/fedora-coreos-39.20240112.3.0-live-rootfs.x86_64.img",
                                "signature": "https://builds.coreos.fedoraproject.org/prod/streams/stable/builds/39.20240112.3.0/x86_64/fedora-coreos-39.20240112.3.0-live-rootfs.x86_64.img.sig",
                                "sha256": "f5fa8728f90ab19cf123c71efc42e7f8ed905c9c59fc81a7679466bebc27294b"
                            }
                        },
                        "raw.xz": {
                            "disk": {
                                "location": "https://builds.coreos.fedoraproject.org/prod/streams/stable/builds/39.20240112.3.0/x86_64/fedora-coreos-39.20240112.3.0-metal.x86_64.raw.xz",
                                "signature": "https://builds.coreos.fedoraproject.org/prod/streams/stable/builds/39.20240112.3.0/x86_64/fedora-coreos-39.20240112.3.0-metal.x86_64.raw.xz.sig",
                                "sha256": "9d58d0b73dd2723b57516e07e0db2cbc754536b22182215fe5ae3bb3625fe562",
                                "uncompressed-sha256": "30b3fa62ec95d3c016556f0ef84b19c633abc50b6d41a99994ebe315cdafda3a"
                            }
                        }
                    }
                },
                "nutanix": {
                    "release": "39.20240112.3.0",
                    "formats": {
                        "qcow2": {
                            "disk": {
                                "location": "https://builds.coreos.fedoraproject.org/prod/streams/stable/builds/39.20240112.3.0/x86_64/fedora-coreos-39.20240112.3.0-nutanix.x86_64.qcow2",
                                "signature": "https://builds.coreos.fedoraproject.org/prod/streams/stable/builds/39.20240112.3.0/x86_64/fedora-coreos-39.20240112.3.0-nutanix.x86_64.qcow2.sig",
                                "sha256": "cb35e286860b27f7cf48dc5388f40faa6e7b9fb89b63f6130143cbd2b6d2a29d"
                            }
                        }
                    }
                },
                "openstack": {
                    "release": "39.20240112.3.0",
                    "formats": {
                        "qcow2.xz": {
                            "disk": {
                                "location": "https://builds.coreos.fedoraproject.org/prod/streams/stable/builds/39.20240112.3.0/x86_64/fedora-coreos-39.20240112.3.0-openstack.x86_64.qcow2.xz",
                                "signature": "https://builds.coreos.fedoraproject.org/prod/streams/stable/builds/39.20240112.3.0/x86_64/fedora-coreos-39.20240112.3.0-openstack.x86_64.qcow2.xz.sig",
                                "sha256": "1712561ab86b1e12e44dedf02eaeb390f6579bd257a12df5a8073e3e33643e13",
                                "uncompressed-sha256": "e754600cc1f9357845beef76f71544db9662fd166113ace00432b476d18b47b8"
                            }
                        }
                    }
                },
                "qemu": {
                    "release": "39.20240112.3.0",
                    "formats": {
                        "qcow2.xz": {
                            "disk": {
                                "location": "https://builds.coreos.fedoraproject.org/prod/streams/stable/builds/39.20240112.3.0/x86_64/fedora-coreos-39.20240112.3.0-qemu.x86_64.qcow2.xz",
                                "signature": "https://builds.coreos.fedoraproject.org/prod/streams/stable/builds/39.20240112.3.0/x86_64/fedora-coreos-39.20240112.3.0-qemu.x86_64.qcow2.xz.sig",
                                "sha256": "58b62252e922f1a22225e44417cba4a4ea54f5da8369aaea627fe7f0cc0827f5",
                                "uncompressed-sha256": "6d9d5fbe980fbe67568461e8916efcd3f586c3ee7270c9ed12cbf7dd68b5e3d3"
                            }
                        }
                    }
                },
                "virtualbox": {
                    "release": "39.20240112.3.0",
                    "formats": {
                        "ova": {
                            "disk": {
                                "location": "https://builds.coreos.fedoraproject.org/prod/streams/stable/builds/39.20240112.3.0/x86_64/fedora-coreos-39.20240112.3.0-virtualbox.x86_64.ova",
                                "signature": "https://builds.coreos.fedoraproject.org/prod/streams/stable/builds/39.20240112.3.0/x86_64/fedora-coreos-39.20240112.3.0-virtualbox.x86_64.ova.sig",
                                "sha256": "bf1c4e09ca29b754e488d79688735ab3e2b602859a35abd39bb816ca801ce394"
                            }
                        }
                    }
                },
                "vmware": {
                    "release": "39.20240112.3.0",
                    "formats": {
                        "ova": {
                            "disk": {
                                "location": "https://builds.coreos.fedoraproject.org/prod/streams/stable/builds/39.20240112.3.0/x86_64/fedora-coreos-39.20240112.3.0-vmware.x86_64.ova",
                                "signature": "https://builds.coreos.fedoraproject.org/prod/streams/stable/builds/39.20240112.3.0/x86_64/fedora-coreos-39.20240112.3.0-vmware.x86_64.ova.sig",
                                "sha256": "6141232d09a5624a31fb56b4d958bd82ebedee79f6983c908a027d320644814a"
                            }
                        }
                    }
                },
                "vultr": {
                    "release": "39.20240112.3.0",
                    "formats": {
                        "raw.xz": {
                            "disk": {
                                "location": "https://builds.coreos.fedoraproject.org/prod/streams/stable/builds/39.20240112.3.0/x86_64/fedora-coreos-39.20240112.3.0-vultr.x86_64.raw.xz",
                                "signature": "https://builds.coreos.fedoraproject.org/prod/streams/stable/builds/39.20240112.3.0/x86_64/fedora-coreos-39.20240112.3.0-vultr.x86_64.raw.xz.sig",
                                "sha256": "474ae3003f2e8f7e9ec740ceee78502ef5519a87d6918e1f561ff240d832860c",
                                "uncompressed-sha256": "5dba1d3ee03eba1521b26e55671d4e2e2d8b2ab29c0f6c99e8c0b61d5c225bfc"
                            }
                        }
                    }
                }
            },
            "images": {
                "aws": {
                    "regions": {
                        "af-south-1": {
                            "release": "39.20240112.3.0",
                            "image": "ami-0c9c49ea6dab7dd53"
                        },
                        "ap-east-1": {
                            "release": "39.20240112.3.0",
                            "image": "ami-0d381c13b70780843"
                        },
                        "ap-northeast-1": {
                            "release": "39.20240112.3.0",
                            "image": "ami-05ba0dee540bec726"
                        },
                        "ap-northeast-2": {
                            "release": "39.20240112.3.0",
                            "image": "ami-0d33dafc98271cfed"
                        },
                        "ap-northeast-3": {
                            "release": "39.20240112.3.0",
                            "image": "ami-0c75737247cd1cd95"
                        },
                        "ap-south-1": {
                            "release": "39.20240112.3.0",
                            "image": "ami-0cfffda68469ef9ba"
                        },
                        "ap-south-2": {
                            "release": "39.20240112.3.0",
                            "image": "ami-06a9e9d6cd1e2be9c"
                        },
                        "ap-southeast-1": {
                            "release": "39.20240112.3.0",
                            "image": "ami-03fb613dbe6c97918"
                        },
                        "ap-southeast-2": {
                            "release": "39.20240112.3.0",
                            "image": "ami-09f15ca8e136bf77f"
                        },
                        "ap-southeast-3": {
                            "release": "39.20240112.3.0",
                            "image": "ami-0ef05977f6c8da287"
                        },
                        "ap-southeast-4": {
                            "release": "39.20240112.3.0",
                            "image": "ami-0e40ca4dae495cf83"
                        },
                        "ca-central-1": {
                            "release": "39.20240112.3.0",
                            "image": "ami-00ccba9a62486dea8"
                        },
                        "ca-west-1": {
                            "release": "39.20240112.3.0",
                            "image": "ami-0e11ab4f92a65c068"
                        },
                        "eu-central-1": {
                            "release": "39.20240112.3.0",
                            "image": "ami-0c26333b53e21db01"
                        },
                        "eu-central-2": {
                            "release": "39.20240112.3.0",
                            "image": "ami-076bdbae1716b8707"
                        },
                        "eu-north-1": {
                            "release": "39.20240112.3.0",
                            "image": "ami-0708e97aacc8ce35a"
                        },
                        "eu-south-1": {
                            "release": "39.20240112.3.0",
                            "image": "ami-08443c0017a641a57"
                        },
                        "eu-south-2": {
                            "release": "39.20240112.3.0",
                            "image": "ami-09ead1fb0ad2b9ae2"
                        },
                        "eu-west-1": {
                            "release": "39.20240112.3.0",
                            "image": "ami-030b283577a1952e8"
                        },
                        "eu-west-2": {
                            "release": "39.20240112.3.0",
                            "image": "ami-0b00f28c8aa40689b"
                        },
                        "eu-west-3": {
                            "release": "39.20240112.3.0",
                            "image": "ami-042f6b09e5d20cad2"
                        },
                        "il-central-1": {
                            "release": "39.20240112.3.0",
                            "image": "ami-0fbb5e346df3ba9cf"
                        },
                        "me-central-1": {
                            "release": "39.20240112.3.0",
                            "image": "ami-082b2fa78cd202f9e"
                        },
                        "me-south-1": {
                            "release": "39.20240112.3.0",
                            "image": "ami-06c7746e01d806014"
                        },
                        "sa-east-1": {
                            "release": "39.20240112.3.0",
                            "image": "ami-0b20c5924042da658"
                        },
                        "us-east-1": {
                            "release": "39.20240112.3.0",
                            "image": "ami-0e28c621aec36772a"
                        },
                        "us-east-2": {
                            "release": "39.20240112.3.0",
                            "image": "ami-058298b7a39e71dee"
                        },
                        "us-west-1": {
                            "release": "39.20240112.3.0",
                            "image": "ami-01d1a17744988d96d"
                        },
                        "us-west-2": {
                            "release": "39.20240112.3.0",
                            "image": "ami-05fe9a391a16d16c3"
                        }
                    }
                },
                "gcp": {
                    "release": "39.20240112.3.0",
                    "project": "fedora-coreos-cloud",
                    "family": "fedora-coreos-stable",
                    "name": "fedora-coreos-39-20240112-3-0-gcp-x86-64"
                },
                "kubevirt": {
                    "release": "39.20240112.3.0",
                    "image": "quay.io/fedora/fedora-coreos-kubevirt:stable",
                    "digest-ref": "quay.io/fedora/fedora-coreos-kubevirt@sha256:bc076398e96b835a1d1cd06a91574bfabce0d14ff1cae7ad5449cf884b825299"
                }
            }
        }
    }
}
